falyx/.pytyped
falyx/__init__.py
falyx/__main__.py
falyx/action/.pytyped
falyx/action/__init__.py
falyx/action/action.py
falyx/action/action_factory.py
falyx/action/action_group.py
falyx/action/action_mixins.py
falyx/action/action_types.py
falyx/action/base_action.py
falyx/action/chained_action.py
falyx/action/confirm_action.py
falyx/action/fallback_action.py
falyx/action/http_action.py
falyx/action/io_action.py
falyx/action/literal_input_action.py
falyx/action/load_file_action.py
falyx/action/menu_action.py
falyx/action/process_action.py
falyx/action/process_pool_action.py
falyx/action/prompt_menu_action.py
falyx/action/save_file_action.py
falyx/action/select_file_action.py
falyx/action/selection_action.py
falyx/action/shell_action.py
falyx/action/signal_action.py
falyx/action/user_input_action.py
falyx/bottom_bar.py
falyx/command.py
falyx/completer.py
falyx/config.py
falyx/console.py
falyx/context.py
falyx/debug.py
falyx/exceptions.py
falyx/execution_registry.py
falyx/falyx.py
falyx/hook_manager.py
falyx/hooks.py
falyx/init.py
falyx/logger.py
falyx/menu.py
falyx/mode.py
falyx/options_manager.py
falyx/parser/.pytyped
falyx/parser/__init__.py
falyx/parser/argument.py
falyx/parser/argument_action.py
falyx/parser/command_argument_parser.py
falyx/parser/parser_types.py
falyx/parser/parsers.py
falyx/parser/signature.py
falyx/parser/utils.py
falyx/prompt_utils.py
falyx/protocols.py
falyx/retry.py
falyx/retry_utils.py
falyx/selection.py
falyx/signals.py
falyx/spinner_manager.py
falyx/tagged_table.py
falyx/themes/__init__.py
falyx/themes/colors.py
falyx/utils.py
falyx/validators.py
falyx/version.py
falyx-0.1.85.dist-info/LICENSE
falyx-0.1.85.dist-info/METADATA
falyx-0.1.85.dist-info/WHEEL
falyx-0.1.85.dist-info/entry_points.txt
falyx-0.1.85.dist-info/RECORD
