Metadata-Version: 2.3
Name: falyx
Version: 0.1.85
Summary: Reliable and introspectable async CLI action framework.
License: MIT
Author: Roland Thomas Jr
Author-email: roland@rtj.dev
Requires-Python: >=3.10
Classifier: License :: OSI Approved :: MIT License
Classifier: Programming Language :: Python :: 3
Classifier: Programming Language :: Python :: 3.10
Classifier: Programming Language :: Python :: 3.11
Classifier: Programming Language :: Python :: 3.12
Classifier: Programming Language :: Python :: 3.13
Requires-Dist: aiohttp (>=3.11,<4.0)
Requires-Dist: prompt_toolkit (>=3.0,<4.0)
Requires-Dist: pydantic (>=2.0,<3.0)
Requires-Dist: python-dateutil (>=2.8,<3.0)
Requires-Dist: python-json-logger (>=3.3.0,<4.0.0)
Requires-Dist: pyyaml (>=6.0,<7.0)
Requires-Dist: rich (>=14.0,<15.0)
Requires-Dist: toml (>=0.10,<0.11)
